package/__init__.py
package/my_cli_app.py
aarushtaskforcetestingvolt-0.1.dist-info/METADATA
aarushtaskforcetestingvolt-0.1.dist-info/WHEEL
aarushtaskforcetestingvolt-0.1.dist-info/entry_points.txt
aarushtaskforcetestingvolt-0.1.dist-info/top_level.txt
aarushtaskforcetestingvolt-0.1.dist-info/RECORD
