Metadata-Version: 2.1
Name: aarushtaskforcetestingvolt
Version: 0.1
Requires-Dist: click
